chemy/__init__.py
chemy/_core.py
chemy-0.0.1.dist-info/LICENSE
chemy-0.0.1.dist-info/WHEEL
chemy-0.0.1.dist-info/METADATA
chemy-0.0.1.dist-info/RECORD
